LICENSE
README.md
setup.py
deso/AccessGroups.py
deso/Associations.py
deso/Derived.py
deso/Identity.py
deso/Media.py
deso/Metadata.py
deso/Posts.py
deso/Sign.py
deso/Social.py
deso/Trade.py
deso/User.py
deso/__init__.py
deso/utils.py
deso.egg-info/PKG-INFO
deso.egg-info/SOURCES.txt
deso.egg-info/dependency_links.txt
deso.egg-info/requires.txt
deso.egg-info/top_level.txt