Metadata-Version: 2.1
Name: deso
Version: 2.3.5
Summary: A python module for deso
Author: ItsAditya (https://itsaditya.xyz)
Author-email: <chaudharyaditya0005@gmail.com>
Keywords: deso,python,bitclout,social media,crypto,blockchain,decentralisation,decentralized social media
Classifier: Development Status :: 1 - Planning
Classifier: Intended Audience :: Developers
Classifier: Programming Language :: Python :: 3
Classifier: Operating System :: Unix
Classifier: Operating System :: MacOS :: MacOS X
Classifier: Operating System :: Microsoft :: Windows
License-File: LICENSE
